{
  "extends": ["tslint:recommended", "tslint-config-prettier"],
  "rules": {
    "quotemark": [
      true,
      "single",
      "jsx-double",
      "jsx-single"
    ],
    "object-literal-sort-keys": false,
    "trailing-comma": false,
    "arrow-parens": false,
    "ordered-imports": false,
    "interface-name": [
      false
    ],
    "no-trailing-whitespace": false,
    "max-line-length": false,
    "jsx-no-lambda": false,
    "no-console": false,
    "no-shadowed-variable": false,
    "indent": [false],
    "member-ordering": false,
    "defaultSeverity": "warning",
  }
}